renamebyreplace/__init__.py
renamebyreplace/core.py
renamebyreplace/locale/es/LC_MESSAGES/renamebyreplace.mo
renamebyreplace/locale/es.po
renamebyreplace/locale/fr/LC_MESSAGES/renamebyreplace.mo
renamebyreplace/locale/fr.po
renamebyreplace/locale/renamebyreplace.pot
renamebyreplace/poethepoet.py
renamebyreplace/tests/test_core.py
renamebyreplace-1.0.0.dist-info/METADATA
renamebyreplace-1.0.0.dist-info/WHEEL
renamebyreplace-1.0.0.dist-info/entry_points.txt
renamebyreplace-1.0.0.dist-info/licenses/LICENSE.txt
renamebyreplace-1.0.0.dist-info/RECORD
