Metadata-Version: 2.4
Name: renamebyreplace
Version: 1.0.0
Summary: Rename files searching substrings in filenames
License: GPL-3
License-File: LICENSE.txt
Author: turulomio
Author-email: turulomio@yahoo.es
Requires-Python: >=3.11
Classifier: License :: Other/Proprietary License
Classifier: Programming Language :: Python :: 3
Classifier: Programming Language :: Python :: 3.11
Classifier: Programming Language :: Python :: 3.12
Classifier: Programming Language :: Python :: 3.13
Classifier: Programming Language :: Python :: 3.14
Requires-Dist: colorama (>=0.4.6)
Project-URL: Homepage, https://github.com/turulomio/renamebyreplace/
Project-URL: Repository, https://github.com/turulomio/renamebyreplace/
Project-URL: changelog, https://github.com/turulomio/renamebyreplace#changelog
